libname/__init__.py
libname/hello.py
helloworldcdaly-0.0.1.dist-info/METADATA
helloworldcdaly-0.0.1.dist-info/WHEEL
helloworldcdaly-0.0.1.dist-info/top_level.txt
helloworldcdaly-0.0.1.dist-info/RECORD
