Metadata-Version: 2.1
Name: helloworldcdaly
Version: 0.0.1
Summary: Hello world.
Author: caolan947 (Caolán Daly)
Author-email: <caolan.day94@gmail.com>
Keywords: python,helloworld,hello,world
Classifier: Development Status :: 1 - Planning
Classifier: Intended Audience :: Developers
Classifier: Programming Language :: Python :: 3
Classifier: Operating System :: Unix
Classifier: Operating System :: MacOS :: MacOS X
Classifier: Operating System :: Microsoft :: Windows
